callapy/__init__.py
callapy/model.py
callapy-0.0.2.dist-info/LICENSE
callapy-0.0.2.dist-info/METADATA
callapy-0.0.2.dist-info/WHEEL
callapy-0.0.2.dist-info/top_level.txt
callapy-0.0.2.dist-info/RECORD
