Metadata-Version: 2.1
Name: callapy
Version: 0.0.2
Summary: Calculating the amount adsorbed from liquid-phase adsorption measurements
Home-page: https://github.com/dejac001/callapy
Author: Robert F. DeJaco
Author-email: dejac001@umn.edu
License: UNKNOWN
Platform: UNKNOWN
Classifier: Programming Language :: Python :: 3
Classifier: License :: OSI Approved :: MIT License
Classifier: Natural Language :: English
Classifier: Operating System :: OS Independent
Classifier: Topic :: Scientific/Engineering
Requires-Python: >=3.6
Requires-Dist: matplotlib (==3.2.1)
Requires-Dist: numpy (==1.18.4)
Requires-Dist: pandas (==1.0.3)
Requires-Dist: Pint (==0.11)
